{
  "slug": "applied-materials-other-chip-monopoly-2026",
  "title": "Everyone Talks About ASML. Nobody Talks About the Other Chip Monopoly.",
  "subtitle": "Applied Materials touches virtually every chip on earth \u2014 and just pulled back 6% while analysts are raising targets to $770.",
  "summary": "Applied Materials is the semiconductor industry's most overlooked monopoly. They cover more fabrication steps than any company alive \u2014 and the AI supercycle is just getting started.",
  "ticker": "AMAT",
  "sector": "ai",
  "sentiment": "bullish",
  "date": "2026-06-29",
  "image": {
    "src": "/img/articles/applied-materials-other-chip-monopoly-2026.jpg",
    "caption": "Applied Materials fabrication equipment processing a silicon wafer in a semiconductor clean room"
  },
  "tags": [
    "AMAT",
    "Applied Materials",
    "semiconductor equipment",
    "AI chips",
    "CHIPS Act",
    "GAA transistors",
    "semiconductor monopoly",
    "wafer fabrication",
    "ASML"
  ],
  "links": [
    {
      "label": "Applied Materials Investor Relations",
      "url": "https://ir.appliedmaterials.com/"
    },
    {
      "label": "Yahoo Finance \u2014 AMAT",
      "url": "https://finance.yahoo.com/quote/AMAT/"
    }
  ],
  "videos": [
    {
      "id": "kDBmDgtf3Sk",
      "title": "New Semiconductor Manufacturing Systems",
      "source": "Applied Materials",
      "url": "https://www.youtube.com/watch?v=kDBmDgtf3Sk",
      "position": "after_2nd_h2"
    }
  ],
  "price": 626.84,
  "bodyHtml": "<p>Everyone knows ASML. Their EUV machines are the only ones on earth that can print the most advanced chip patterns. It is a true monopoly and the market has priced it accordingly. Everyone also knows TSMC \u2014 the foundry where Apple, Nvidia, and AMD line up and wait their turn.</p><p>But there is a third company that almost never gets the headline treatment. A company that touches more steps of the chip fabrication process than anyone alive. Strip away lithography \u2014 ASML's one trick \u2014 and Applied Materials handles virtually everything else. Deposition. Etch. Chemical-mechanical planarization. Ion implantation. Inspection. Advanced packaging. If you are building a chip, you are buying from Applied Materials whether you realize it or not.</p><!-- VIDEO 1 --><p>The stock just pulled back hard from its weekly high, dropping over six percent while the broader semiconductor complex caught a bid and gave it all back. The market is getting nervous about multiples and China exposure. But the underlying business just posted its third consecutive quarter of accelerating revenue, guided the next quarter to nearly nine billion dollars, and has analysts from Jefferies to Wells Fargo to Bank of America racing to raise price targets past seven hundred.</p><p>Here is why Applied Materials matters more than most investors understand. The semiconductor industry is moving to gate-all-around transistors at the leading edge \u2014 the next generation after FinFET. Every new transistor geometry requires more process steps: more deposition layers, more etch cycles, more polishing passes. AMAT's own management estimated that every hundred thousand wafer starts at a GAA node generates over a billion dollars in incremental revenue for the company. That is not a forecast. That is math baked into the physics of smaller transistors.</p><p>Then there is advanced packaging. As the industry moves toward chiplets \u2014 stuffing multiple specialized dies into a single package \u2014 the back-end of the fab has become just as critical as the front-end. HBM memory for AI accelerators needs through-silicon vias and copper microbumps. Nvidia's next-generation architectures need hybrid bonding at densities that did not exist three years ago. Applied Materials is the number one supplier of process equipment for advanced packaging worldwide.</p><p>The CHIPS Act pours another accelerant on top. Over fifty-two billion dollars authorized for semiconductor manufacturing on American soil. Intel in Ohio, TSMC in Arizona, Samsung in Texas, Micron in Idaho. Every single one of those fabs needs Applied Materials equipment across six or more process categories. You cannot build a leading-edge American fab without this company. It is not a preference \u2014 it is a requirement.</p><p>The financials confirm the story. Twenty-nine billion dollars in trailing revenue growing over eleven percent year-over-year. Forty-nine percent gross margins on physical capital equipment \u2014 borderline absurd for a company that manufactures machines the size of houses. Quarter by quarter the acceleration is visible: six-point-eight billion in October, seven billion in January, seven-point-nine billion in April. Next quarter is guided to nearly nine billion. That is a company compounding into a supercycle.</p><p>The risk is real. China revenue has already dropped from roughly forty-five percent of sales to twenty-five percent as export controls tighten, and management has flagged additional headwinds from further restrictions. Chinese competitors are making noise in deposition and CMP. The stock still trades at a trailing premium that prices in plenty of good news.</p><p>But here is the thing about monopolies. You do not buy them when they are cheap. You buy them when the thesis is intact and the market gives you a window. The thesis on Applied Materials is that every advanced chip built through the end of this decade \u2014 for AI, for automotive, for defense, for data centers \u2014 requires more of their equipment per wafer than the last. The demand is not cyclical. It is architectural. Baked into the physics of smaller transistors and bigger models and the geopolitical mandate to build fabs on three continents at once.</p><p>ASML is a great company. TSMC is a great company. But if you want the one name that touches more of the semiconductor supply chain than any other \u2014 the company that wins regardless of which customer or node or geography leads the next cycle \u2014 that name is Applied Materials. And it just went on sale.</p><p class=\"disclosure\"><em>Disclosure: The Signal holds no position in AMAT. Positions may change. This is not financial advice.</em></p>"
}